dlpx/__init__.py
dlpx/virtualization/__init__.py
dlpx/virtualization/common/__init__.py
dlpx/virtualization/common/_common_classes.py
dlpx/virtualization/common/exceptions.py
dlpx/virtualization/common/util.py
dvp_common-5.0.1.dist-info/LICENSE
dvp_common-5.0.1.dist-info/METADATA
dvp_common-5.0.1.dist-info/WHEEL
dvp_common-5.0.1.dist-info/top_level.txt
dvp_common-5.0.1.dist-info/RECORD
