Metadata-Version: 2.1
Name: dvp-common
Version: 5.0.1
Home-page: https://developer.delphix.com
Author: Delphix
Author-email: virtualization-plugins@delphix.com
Classifier: Development Status :: 5 - Production/Stable
Classifier: Programming Language :: Python
Classifier: Programming Language :: Python :: 3.11
Classifier: License :: OSI Approved :: Apache Software License
Classifier: Operating System :: OS Independent
Requires-Python: >=3.11, <3.12
License-File: LICENSE
Requires-Dist: dvp-api==1.9.0
Requires-Dist: six<1.17,>=1.16
